acet/__init__.py
acet/engine.py
acet/agents/__init__.py
acet/agents/react.py
acet/core/__init__.py
acet/core/budget.py
acet/core/interfaces.py
acet/core/models.py
acet/curators/__init__.py
acet/curators/standard.py
acet/generators/__init__.py
acet/generators/llm.py
acet/integrations/__init__.py
acet/integrations/langchain.py
acet/llm/__init__.py
acet/llm/base.py
acet/llm/providers/__init__.py
acet/llm/providers/anthropic.py
acet/llm/providers/litellm_provider.py
acet/llm/providers/openai.py
acet/reflectors/__init__.py
acet/reflectors/llm.py
acet/retrieval/__init__.py
acet/retrieval/dedup.py
acet/retrieval/ranker.py
acet/storage/__init__.py
acet/storage/custom_example.py
acet/storage/memory.py
acet/storage/postgres.py
acet/storage/sqlite.py
acet-1.0.10.dist-info/licenses/LICENSE
acet-1.0.10.dist-info/METADATA
acet-1.0.10.dist-info/WHEEL
acet-1.0.10.dist-info/top_level.txt
acet-1.0.10.dist-info/RECORD
