Metadata-Version: 2.4
Name: acet
Version: 1.0.10
Summary: Agentic Context Toolkit: context delta learning for adaptive LLM agents
Author-email: Lionel <lioarce1@gmail.com>
License: MIT
Project-URL: Homepage, https://github.com/lioarce01/agentic-context-toolkit
Project-URL: Documentation, https://github.com/lioarce01/agentic-context-toolkit
Project-URL: Repository, https://github.com/lioarce01/agentic-context-toolkit
Project-URL: CHANGELOG, https://github.com/lioarce01/agentic-context-toolkit/blob/main/CHANGELOG.md
Project-URL: Issues, https://github.com/lioarce01/agentic-context-toolkit/issues
Keywords: llm,agents,context,rag,ai,machine-learning,context-engineering,self-improving
Classifier: Development Status :: 4 - Beta
Classifier: Intended Audience :: Developers
Classifier: Intended Audience :: Science/Research
Classifier: License :: OSI Approved :: MIT License
Classifier: Programming Language :: Python :: 3.12
Classifier: Topic :: Scientific/Engineering :: Artificial Intelligence
Classifier: Topic :: Software Development :: Libraries :: Python Modules
Classifier: Typing :: Typed
Requires-Python: >=3.12
License-File: LICENSE
Requires-Dist: pydantic>=2.9
Requires-Dist: httpx>=0.27
Requires-Dist: tiktoken>=0.8
Requires-Dist: numpy>=2.1
Requires-Dist: aiosqlite>=0.20
Requires-Dist: sentence-transformers>=3.2
Requires-Dist: sqlalchemy>=2.0
Requires-Dist: structlog>=24.0
Requires-Dist: python-dotenv>=1.0
Provides-Extra: openai
Requires-Dist: openai>=1.54; extra == "openai"
Provides-Extra: anthropic
Requires-Dist: anthropic>=0.39; extra == "anthropic"
Provides-Extra: litellm
Requires-Dist: litellm>=1.52; extra == "litellm"
Provides-Extra: ollama
Requires-Dist: ollama>=0.4; extra == "ollama"
Provides-Extra: faiss
Requires-Dist: faiss-cpu>=1.9; extra == "faiss"
Provides-Extra: chroma
Requires-Dist: chromadb>=0.5; extra == "chroma"
Provides-Extra: postgres
Requires-Dist: psycopg2-binary>=2.9; extra == "postgres"
Requires-Dist: pgvector>=0.3; extra == "postgres"
Provides-Extra: langchain
Requires-Dist: langchain>=0.3; extra == "langchain"
Requires-Dist: langchain-community>=0.3; extra == "langchain"
Provides-Extra: llamaindex
Requires-Dist: llama-index>=0.11; extra == "llamaindex"
Provides-Extra: dev
Requires-Dist: pytest>=8.3; extra == "dev"
Requires-Dist: pytest-cov>=6.0; extra == "dev"
Requires-Dist: pytest-asyncio>=0.24; extra == "dev"
Requires-Dist: pytest-benchmark>=4.0; extra == "dev"
Requires-Dist: mypy>=1.13; extra == "dev"
Requires-Dist: ruff>=0.7; extra == "dev"
Requires-Dist: black>=24.10; extra == "dev"
Requires-Dist: sphinx>=8.0; extra == "dev"
Requires-Dist: sphinx-rtd-theme>=3.0; extra == "dev"
Requires-Dist: matplotlib>=3.9; extra == "dev"
Provides-Extra: all
Requires-Dist: openai>=1.54; extra == "all"
Requires-Dist: anthropic>=0.39; extra == "all"
Requires-Dist: litellm>=1.52; extra == "all"
Requires-Dist: ollama>=0.4; extra == "all"
Requires-Dist: faiss-cpu>=1.9; extra == "all"
Requires-Dist: chromadb>=0.5; extra == "all"
Requires-Dist: psycopg2-binary>=2.9; extra == "all"
Requires-Dist: pgvector>=0.3; extra == "all"
Requires-Dist: langchain>=0.3; extra == "all"
Requires-Dist: langchain-community>=0.3; extra == "all"
Requires-Dist: llama-index>=0.11; extra == "all"
Dynamic: license-file
